deeplay/__init__.py
deeplay/decorators.py
deeplay/list.py
deeplay/meta.py
deeplay/module.py
deeplay/shapes.py
deeplay/trainer.py
deeplay/activelearning/__init__.py
deeplay/activelearning/criterion.py
deeplay/activelearning/data.py
deeplay/activelearning/strategies/__init__.py
deeplay/activelearning/strategies/strategy.py
deeplay/activelearning/strategies/uncertainty.py
deeplay/activelearning/strategies/uniform.py
deeplay/activelearning/strategies/adversarial/__init__.py
deeplay/activelearning/strategies/adversarial/adversarial.py
deeplay/applications/__init__.py
deeplay/applications/application.py
deeplay/applications/autoencoders/__init__.py
deeplay/applications/autoencoders/vae.py
deeplay/applications/autoencoders/wae.py
deeplay/applications/classification/__init__.py
deeplay/applications/classification/binary.py
deeplay/applications/classification/categorical.py
deeplay/applications/classification/classifier.py
deeplay/applications/classification/multilabel.py
deeplay/applications/detection/__init__.py
deeplay/applications/detection/lodestar/__init__.py
deeplay/applications/detection/lodestar/dataset.py
deeplay/applications/detection/lodestar/lodestar.py
deeplay/applications/detection/lodestar/transforms.py
deeplay/applications/regression/__init__.py
deeplay/applications/regression/regressor.py
deeplay/blocks/__init__.py
deeplay/blocks/base.py
deeplay/blocks/block.py
deeplay/blocks/la.py
deeplay/blocks/lan.py
deeplay/blocks/land.py
deeplay/blocks/lanu.py
deeplay/blocks/ls.py
deeplay/blocks/plan.py
deeplay/blocks/recurrentblock.py
deeplay/blocks/residual.py
deeplay/blocks/sequential.py
deeplay/blocks/conv/__init__.py
deeplay/blocks/conv/conv2d.py
deeplay/blocks/conv/conv2d.pyi
deeplay/blocks/linear/__init__.py
deeplay/blocks/linear/linear.py
deeplay/blocks/sequence/__init__.py
deeplay/blocks/sequence/sequence1d.py
deeplay/callbacks/__init__.py
deeplay/callbacks/history.py
deeplay/callbacks/progress.py
deeplay/components/__init__.py
deeplay/components/dict.py
deeplay-0.1.4.dist-info/METADATA
deeplay-0.1.4.dist-info/WHEEL
deeplay-0.1.4.dist-info/top_level.txt
deeplay-0.1.4.dist-info/RECORD
