Metadata-Version: 2.4
Name: deeplay
Version: 0.1.4
Summary: An AI-powered platform for advancing deep learning research and applications, developed by DeepTrackAI.
Home-page: https://github.com/DeepTrackAI/deeplay
Author: Benjamin Midtvedt, Jesus Pineda, Henrik Klein Moberg, Harshith Bachimanchi, Mirja Granfors, Alex Lech, Carlo Manzo, Giovanni Volpe
License: MIT
Keywords: AI,Deep Learning,Machine Learning,Data Science,Research Platform,Artificial Intelligence,Technology
Requires-Python: >=3.9
Requires-Dist: numpy
Requires-Dist: matplotlib
Requires-Dist: torch>2.3
Requires-Dist: lightning
Requires-Dist: torchmetrics
Requires-Dist: torchvision
Requires-Dist: torch-geometric
Requires-Dist: kornia
Requires-Dist: scipy
Requires-Dist: scikit-image
Requires-Dist: rich
Requires-Dist: dill
Dynamic: author
Dynamic: description
Dynamic: description-content-type
Dynamic: home-page
Dynamic: keywords
Dynamic: license
Dynamic: requires-dist
Dynamic: requires-python
Dynamic: summary
